py_easy_rest_mongo_motor_repo/__init__.py
py_easy_rest_mongo_motor_repo-0.1.5.dist-info/METADATA
py_easy_rest_mongo_motor_repo-0.1.5.dist-info/WHEEL
py_easy_rest_mongo_motor_repo-0.1.5.dist-info/top_level.txt
py_easy_rest_mongo_motor_repo-0.1.5.dist-info/RECORD
